virementmaitrise/__init__.py
virementmaitrise/api_requestor.py
virementmaitrise/constants.py
virementmaitrise/crypto.py
virementmaitrise/environments.py
virementmaitrise/error.py
virementmaitrise/fintecture_object.py
virementmaitrise/fintecture_response.py
virementmaitrise/http_client.py
virementmaitrise/multipart_data_generator.py
virementmaitrise/oauth.py
virementmaitrise/object_classes.py
virementmaitrise/request_metrics.py
virementmaitrise/util.py
virementmaitrise/webhook.py
virementmaitrise/api_resources/__init__.py
virementmaitrise/api_resources/account.py
virementmaitrise/api_resources/account_holder.py
virementmaitrise/api_resources/ais.py
virementmaitrise/api_resources/application.py
virementmaitrise/api_resources/customer.py
virementmaitrise/api_resources/ephemeral_key.py
virementmaitrise/api_resources/error_object.py
virementmaitrise/api_resources/list_object.py
virementmaitrise/api_resources/payment.py
virementmaitrise/api_resources/payout.py
virementmaitrise/api_resources/pis.py
virementmaitrise/api_resources/provider.py
virementmaitrise/api_resources/refund.py
virementmaitrise/api_resources/search_result_object.py
virementmaitrise/api_resources/test_account.py
virementmaitrise/api_resources/abstract/__init__.py
virementmaitrise/api_resources/abstract/api_resource.py
virementmaitrise/api_resources/abstract/createable_api_resource.py
virementmaitrise/api_resources/abstract/custom_method.py
virementmaitrise/api_resources/abstract/deletable_api_resource.py
virementmaitrise/api_resources/abstract/listable_api_resource.py
virementmaitrise/api_resources/abstract/nested_resource_class_methods.py
virementmaitrise/api_resources/abstract/searchable_api_resource.py
virementmaitrise/api_resources/abstract/singleton_api_resource.py
virementmaitrise/api_resources/abstract/test_helpers.py
virementmaitrise/api_resources/abstract/updateable_api_resource.py
virementmaitrise/api_resources/abstract/verify_mixin.py
virementmaitrise/api_resources/test_helpers/__init__.py
virementmaitrise-2.1.1.dist-info/LICENSE
virementmaitrise-2.1.1.dist-info/METADATA
virementmaitrise-2.1.1.dist-info/WHEEL
virementmaitrise-2.1.1.dist-info/top_level.txt
virementmaitrise-2.1.1.dist-info/RECORD
