Metadata-Version: 2.1
Name: virementmaitrise
Version: 2.1.1
Summary: Python bindings for the Virement Maitrise API (powered by Fintecture)
Author-email: Société Générale <support@virementmaitrise.societegenerale.eu>
License: The MIT License
Project-URL: Homepage, https://console.virementmaitrise.societegenerale.eu
Project-URL: Documentation, https://doc.virementmaitrise.societegenerale.eu
Project-URL: Repository, https://github.com/virementmaitrise/virementmaitrise-sdk-python
Project-URL: Bug Tracker, https://github.com/virementmaitrise/virementmaitrise-sdk-python/issues
Project-URL: Changelog, https://github.com/virementmaitrise/virementmaitrise-sdk-python/blob/master/CHANGELOG.md
Keywords: virementmaitrise,api,payments
Classifier: Development Status :: 5 - Production/Stable
Classifier: Intended Audience :: Developers
Classifier: License :: OSI Approved :: MIT License
Classifier: Operating System :: OS Independent
Classifier: Programming Language :: Python
Classifier: Programming Language :: Python :: 3
Classifier: Programming Language :: Python :: 3.10
Classifier: Programming Language :: Python :: 3.11
Classifier: Programming Language :: Python :: 3.12
Classifier: Programming Language :: Python :: 3.13
Classifier: Topic :: Software Development :: Libraries :: Python Modules
Requires-Python: >=3.10
License-File: LICENSE
Requires-Dist: requests >=2.32.5
Requires-Dist: cffi >=1.15
Requires-Dist: cryptography <37.0,>=3.4.8 ; python_version < "3.12"
Requires-Dist: cryptography >=37.0.4 ; python_version >= "3.12"
Requires-Dist: pycryptodome ==3.23.0 ; sys_platform == "windows"
